{
  "BusinessTypes": {
    "HairSalon": "سالن آرایش مو",
    "MakeupStudio": "استودیو میکاپ",
    "NailStudio": "سالن ناخن",
    "SkinCareClinic": "کلینیک مراقبت پوست",
    "SpaAndMassage": "اسپا و ماساژ",
    "LaserClinic": "کلینیک لیزر",
    "TattooStudio": "استودیو تاتو",
    "DentalClinic": "کلینیک دندانپزشکی",
    "FitnessWellnessCenter": "مرکز تناسب اندام و سلامت",
    "AestheticClinic": "کلینیک زیبایی",
    "Barbershop": "آرایشگاه مردانه"
  },
  "ServiceCategories": {
    "HaircutMen": "کوتاهی موی مردانه",
    "HaircutWomen": "کوتاهی موی زنانه",
    "KidsHaircut": "کوتاهی موی کودک",
    "BeardTrim": "اصلاح ریش",
    "Shaving": "اصلاح صورت",
    "HairStyling": "مدل دادن مو",
    "HairColoring": "رنگ مو",
    "HairHighlightsBalayage": "هایلایت و بالیاژ",
    "HairExtensions": "اکستنشن مو",
    "HairKeratinTreatment": "کراتین مو",
    "HairStraightening": "صاف کردن مو",
    "HairPerming": "فر کردن مو",
    "ScalpTreatment": "درمان پوست سر",

    "BridalMakeup": "میکاپ عروس",
    "EngagementMakeup": "میکاپ نامزدی",
    "CasualMakeup": "میکاپ روزانه",
    "EventMakeup": "میکاپ مجلسی",
    "PermanentMakeup": "میکاپ دائم",
    "Microblading": "میکروبلیدینگ",
    "Microshading": "میکروشیدینگ",
    "EyelashExtensions": "اکستنشن مژه",
    "EyelashLift": "لیفت مژه",
    "EyebrowShaping": "فرم‌دهی ابرو",
    "EyebrowTinting": "رنگ ابرو",

    "NailPolish": "لاک ساده",
    "GelPolish": "لاک ژل",
    "AcrylicNails": "ناخن اکریلیک",
    "GelNails": "ناخن ژل",
    "ManicureClassic": "مانیکور کلاسیک",
    "ManicureSpa": "مانیکور اسپا",
    "PedicureClassic": "پدیکور کلاسیک",
    "PedicureSpa": "پدیکور اسپا",
    "NailExtensions": "اکستنشن ناخن",
    "NailRepair": "ترمیم ناخن",
    "NailArtBasic": "طراحی ناخن ساده",
    "NailArtAdvanced": "طراحی ناخن حرفه‌ای",

    "FacialBasic": "فیشال ساده",
    "FacialDeepCleansing": "فیشال پاکسازی عمیق",
    "FacialAntiAging": "فیشال ضدپیری",
    "FacialBrightening": "فیشال روشن‌کننده",
    "AcneTreatment": "درمان آکنه",
    "RosaceaTreatment": "درمان روزاسه",
    "PigmentationTreatment": "درمان لک پوستی",
    "ChemicalPeel": "لایه‌برداری شیمیایی",
    "Microdermabrasion": "میکرودرم ابریژن",
    "Hydrafacial": "هیدرافیشال",
    "PRPTherapy": "پی آر پی (PRP)",
    "Mesotherapy": "مزوتراپی",

    "MassageRelaxation": "ماساژ ریلکسی",
    "MassageTherapeutic": "ماساژ درمانی",
    "MassageSwedish": "ماساژ سوئدی",
    "MassageThai": "ماساژ تایلندی",
    "MassageHotStone": "ماساژ سنگ داغ",
    "MassageAromatherapy": "ماساژ آروماتراپی",
    "MassageSports": "ماساژ ورزشی",
    "MassageDeepTissue": "ماساژ بافت عمیق",
    "MassageReflexology": "رفلکسولوژی",
    "MassagePregnancy": "ماساژ دوران بارداری",
    "CoupleMassage": "ماساژ زوج",
    "SpaBodyWrap": "رپ بدن",
    "SpaScrub": "اسکراب بدن",
    "Sauna": "سونا",
    "SteamRoom": "اتاق بخار",
    "Jacuzzi": "جکوزی",
    "WellnessDetoxProgram": "برنامه سم‌زدایی",

    "LaserHairRemoval": "لیزر موهای زائد",
    "ElectrolysisHairRemoval": "الکترولیز موهای زائد",
    "IPLHairRemoval": "اپیلاسیون با IPL",
    "LaserSkinRejuvenation": "لیزر جوانسازی پوست",
    "TattooLaserRemoval": "پاک کردن تاتو با لیزر",
    "VascularLaserTreatment": "درمان عروق با لیزر",
    "PigmentationLaserTreatment": "درمان لک با لیزر",

    "TattooDesignSmall": "تاتو کوچک",
    "TattooDesignMedium": "تاتو متوسط",
    "TattooDesignLarge": "تاتو بزرگ",
    "TattooCoverUp": "کاور تاتو",
    "TattooRemovalLaser": "پاک کردن تاتو",
    "HennaDesign": "طرح حنا",
    "PiercingEar": "پیرسینگ گوش",
    "PiercingNose": "پیرسینگ بینی",
    "PiercingBody": "پیرسینگ بدن",

    "TeethWhitening": "بلیچینگ دندان",
    "DentalVeneers": "ونیر دندانی",
    "DentalImplants": "ایمپلنت",
    "OrthodonticsBraces": "ارتودنسی (براکت)",
    "OrthodonticsAligners": "ارتودنسی نامرئی",
    "CosmeticDentistry": "دندانپزشکی زیبایی",
    "DentalCheckup": "ویزیت دندانپزشکی",
    "DentalCleaning": "جرم‌گیری دندان",
    "RootCanalTreatment": "عصب‌کشی",

    "PersonalTraining": "تمرین خصوصی",
    "YogaClass": "کلاس یوگا",
    "PilatesClass": "کلاس پیلاتس",
    "CrossfitSession": "کراس‌فیت",
    "ZumbaClass": "کلاس زومبا",
    "StrengthTraining": "تمرین قدرتی",
    "CardioTraining": "تمرین هوازی",
    "NutritionConsultation": "مشاوره تغذیه",
    "MeditationSession": "مدیتیشن",
    "WellnessCoaching": "کوچینگ سلامت",

    "BotoxInjection": "تزریق بوتاکس",
    "DermalFillers": "فیلر پوستی",
    "LipEnhancement": "حجم‌دهی لب",
    "SkinTightening": "لیفت پوست",
    "CoolSculpting": "کرایولیپولیز (کول‌اسکالپتینگ)",
    "BodyContouring": "فرم‌دهی بدن",
    "ThreadLift": "لیفت با نخ",
    "PlateletRichPlasma": "پی آر پی (PRP)",
    "HairRestoration": "ترمیم مو",

    "MenHaircut": "کوتاهی موی مردانه",
    "FadeHaircut": "کوتاهی فید",
    "BeardStyling": "استایل ریش",
    "HairColorMen": "رنگ موی مردانه"
  }
}
